{
    "agent": null,
    "applicant": "Mr Keith Perryman",
    "application_number": "16DIS/1297",
    "application_number_provisional": null,
    "application_type": "Discharge of Conditions",
    "case_officer_name": "Jon Woodward",
    "case_officer_number": "01512333021",
    "comments_until_date": "2016-05-26",
    "committee_date": null,
    "current_status": "REGISTERED",
    "decision": null,
    "decision_date": null,
    "description": "To discharge conditions 3, 4 and 8 attached to 15F/2900",
    "determination_level": null,
    "development_type": "alterations to building",
    "extract_datetime": "2017-02-06 01:27:50.738907",
    "geo_easting": 338524,
    "geo_latitude": "53.3888797056895",
    "geo_longitude": "-2.92581884090226",
    "geo_northing": 388404,
    "northgate_id": 997561,
    "parishes": "City South",
    "planning_officer_name": "Jon Woodward",
    "postcode": "L17 1AG",
    "received_date": "2016-05-26",
    "site_address": "Former Potting Shed/Greenbank Road, Adjacent to walled garden, Liverpool, L17 1AG",
    "url": "http://northgate.liverpool.gov.uk/PlanningExplorer17/Generic/StdDetails.aspx?PT=Planning%20Applications%20On-Line&TYPE=PL/PlanningPK.xml&PARAM0=997561&XSLT=/PlanningExplorer17/SiteFiles/Skins/Liverpool_WIP/xslt/PL/PLDetails.xslt&FT=Planning%20Application%20Details&PUBLIC=Y&XMLSIDE=/PlanningExplorer17/SiteFiles/Skins/Liverpool_WIP/Menus/PL.xml&DAURI=PLANNING",
    "wards": "Greenbank"
}