{
    "agent": null,
    "applicant": "Liverpool Mutual Homes",
    "application_number": "16DIS/1843",
    "application_number_provisional": null,
    "application_type": "Discharge of Conditions",
    "case_officer_name": "Hannah Ellison",
    "case_officer_number": null,
    "comments_until_date": "2016-07-21",
    "committee_date": null,
    "current_status": "REGISTERED",
    "decision": null,
    "decision_date": null,
    "description": "To discharge conditions 1-8 attached to 16F/0749",
    "determination_level": null,
    "development_type": "Unknown",
    "extract_datetime": "2016-12-19 01:32:19.249347",
    "geo_easting": 338473,
    "geo_latitude": "53.3988587448736",
    "geo_longitude": "-2.92680253350362",
    "geo_northing": 389515,
    "northgate_id": 1006300,
    "parishes": "City North",
    "planning_officer_name": "Hannah Ellison",
    "postcode": "L15 4JN",
    "received_date": "2016-07-15",
    "site_address": "62 Wellington Road, Liverpool, L15 4JN",
    "url": "http://northgate.liverpool.gov.uk/PlanningExplorer17/Generic/StdDetails.aspx?PT=Planning%20Applications%20On-Line&TYPE=PL/PlanningPK.xml&PARAM0=1006300&XSLT=/PlanningExplorer17/SiteFiles/Skins/Liverpool_WIP/xslt/PL/PLDetails.xslt&FT=Planning%20Application%20Details&PUBLIC=Y&XMLSIDE=/PlanningExplorer17/SiteFiles/Skins/Liverpool_WIP/Menus/PL.xml&DAURI=PLANNING",
    "wards": "Wavertree"
}