{
    "agent": null,
    "applicant": "Indigo Sun Retail Ltd",
    "application_number": "16F/3036",
    "application_number_provisional": null,
    "application_type": "Full Planning Permission",
    "case_officer_name": "Kate Mawdsley",
    "case_officer_number": null,
    "comments_until_date": "2017-01-06",
    "committee_date": null,
    "current_status": "REGISTERED",
    "decision": null,
    "decision_date": null,
    "description": "To change use from retail to a sunbed salon",
    "determination_level": null,
    "development_type": "change of use (inc buildings)",
    "extract_datetime": "2017-01-15 01:19:06.239253",
    "geo_easting": 339313,
    "geo_latitude": "53.3889531511511",
    "geo_longitude": "-2.9139567029747",
    "geo_northing": 388402,
    "northgate_id": 1025762,
    "parishes": "City South",
    "planning_officer_name": "Kate Mawdsley",
    "postcode": "L15 9EN",
    "received_date": "2016-12-12",
    "site_address": "21-22 Smithdown Place, Liverpool, L15 9EN",
    "url": "http://northgate.liverpool.gov.uk/PlanningExplorer17/Generic/StdDetails.aspx?PT=Planning%20Applications%20On-Line&TYPE=PL/PlanningPK.xml&PARAM0=1025762&XSLT=/PlanningExplorer17/SiteFiles/Skins/Liverpool_WIP/xslt/PL/PLDetails.xslt&FT=Planning%20Application%20Details&PUBLIC=Y&XMLSIDE=&DAURI=PLANNING",
    "wards": "Church"
}