{
    "agent": null,
    "applicant": "Shelborn Asset Management Limited",
    "application_number": "16A/2845",
    "application_number_provisional": null,
    "application_type": "Advertisement",
    "case_officer_name": "James Chatterton",
    "case_officer_number": null,
    "comments_until_date": "2016-12-28",
    "committee_date": null,
    "current_status": "REGISTERED",
    "decision": null,
    "decision_date": null,
    "description": "To display wall mounted sign.",
    "determination_level": null,
    "development_type": "advert: Fascia (non-illum)",
    "extract_datetime": "2016-12-23 01:19:18.763393",
    "geo_easting": 334129,
    "geo_latitude": "53.40832746932",
    "geo_longitude": "-2.99235648702023",
    "geo_northing": 390627,
    "northgate_id": 1021481,
    "parishes": "City Centre",
    "planning_officer_name": "James Chatterton",
    "postcode": "L2 2NZ",
    "received_date": "2016-11-10",
    "site_address": "Tithebarn House, Tithebarn Street, Liverpool, L2 2NZ",
    "url": "http://northgate.liverpool.gov.uk/PlanningExplorer17/Generic/StdDetails.aspx?PT=Planning%20Applications%20On-Line&TYPE=PL/PlanningPK.xml&PARAM0=1021481&XSLT=/PlanningExplorer17/SiteFiles/Skins/Liverpool_WIP/xslt/PL/PLDetails.xslt&FT=Planning%20Application%20Details&PUBLIC=Y&XMLSIDE=/PlanningExplorer17/SiteFiles/Skins/Liverpool_WIP/Menus/PL.xml&DAURI=PLANNING",
    "wards": "Central"
}