{
    "agent": null,
    "applicant": "Thomson & Moulton",
    "application_number": "15T/3093",
    "application_number_provisional": null,
    "application_type": "Tree Works Consent",
    "case_officer_name": "Matthew Potier",
    "case_officer_number": null,
    "comments_until_date": "2016-01-25",
    "committee_date": null,
    "current_status": "FINAL DECISION",
    "decision": "Approve with Conditions",
    "decision_date": "2016-01-25",
    "description": "To carry out treeworks",
    "determination_level": "Case Officer",
    "development_type": "Treeworks",
    "extract_datetime": "2016-11-20 18:10:08.728919",
    "geo_easting": 342342,
    "geo_northing": 387280,
    "northgate_id": 974702,
    "parishes": "City South",
    "planning_officer_name": "Matthew Potier",
    "postcode": null,
    "received_date": "2015-12-10",
    "site_address": "Byron Court, 20 Woolton Park, Liverpool, L25",
    "url": "http://northgate.liverpool.gov.uk/PlanningExplorer17/Generic/StdDetails.aspx?PT=Planning%20Applications%20On-Line&TYPE=PL/PlanningPK.xml&PARAM0=974702&XSLT=/PlanningExplorer17/SiteFiles/Skins/Liverpool_WIP/xslt/PL/PLDetails.xslt&FT=Planning%20Application%20Details&PUBLIC=Y&XMLSIDE=/PlanningExplorer17/SiteFiles/Skins/Liverpool_WIP/Menus/PL.xml&DAURI=PLANNING",
    "wards": "Woolton"
}