{
    "agent": null,
    "applicant": "University of Liverpool",
    "application_number": "16L/0143",
    "application_number_provisional": null,
    "application_type": "Listed Building",
    "case_officer_name": "Anne-Marie Piedot",
    "case_officer_number": "01512333021",
    "comments_until_date": "2016-02-16",
    "committee_date": null,
    "current_status": "FINAL DECISION",
    "decision": "Approve with Conditions",
    "decision_date": "2016-02-23",
    "description": "To install external louvre to the rear elevation.",
    "determination_level": "Case Officer",
    "development_type": "alterations to building",
    "extract_datetime": "2017-05-12 01:48:15.544641",
    "geo_easting": 335916,
    "geo_latitude": "53.406301046502",
    "geo_longitude": "-2.96542817361633",
    "geo_northing": 390377,
    "northgate_id": 977140,
    "parishes": "City Centre",
    "planning_officer_name": "Anne-Marie Piedot",
    "postcode": "L69 3DQ",
    "received_date": "2016-01-15",
    "site_address": "Victoria Gallery and Museum, Brownlow Hill, Liverpool, L69 3DQ",
    "url": "http://northgate.liverpool.gov.uk/PlanningExplorer17/Generic/StdDetails.aspx?PT=Planning%20Applications%20On-Line&TYPE=PL/PlanningPK.xml&PARAM0=977140&XSLT=/PlanningExplorer17/SiteFiles/Skins/Liverpool_WIP/xslt/PL/PLDetails.xslt&FT=Planning%20Application%20Details&PUBLIC=Y&XMLSIDE=&DAURI=PLANNING",
    "wards": "Central"
}