{
    "agent": null,
    "applicant": "Henry Space Development Limited",
    "application_number": "16L/0266",
    "application_number_provisional": null,
    "application_type": "Listed Building",
    "case_officer_name": "Chris Ridland",
    "case_officer_number": "01512333021",
    "comments_until_date": "2016-03-17",
    "committee_date": null,
    "current_status": "FINAL DECISION",
    "decision": "Approve with Conditions",
    "decision_date": "2016-06-30",
    "description": "To convert (with partial demolition) existing building in conjunction with redevelopment of site with the erection of 4-8 storey building containing 151 residential units with ground floor communal use, with associated access, parking, servicing and landscaping.",
    "determination_level": "Case Officer",
    "development_type": "change of use (inc buildings), partial demolition",
    "extract_datetime": "2016-11-20 21:03:35.540312",
    "geo_easting": 334970,
    "geo_latitude": null,
    "geo_longitude": null,
    "geo_northing": 389785,
    "northgate_id": 979920,
    "parishes": "City Centre",
    "planning_officer_name": "Chris Ridland",
    "postcode": "L1 5AG",
    "received_date": "2016-01-27",
    "site_address": "118-124  Duke Street, Liverpool, L1 5AG",
    "url": "http://northgate.liverpool.gov.uk/PlanningExplorer17/Generic/StdDetails.aspx?PT=Planning%20Applications%20On-Line&TYPE=PL/PlanningPK.xml&PARAM0=979920&XSLT=/PlanningExplorer17/SiteFiles/Skins/Liverpool_WIP/xslt/PL/PLDetails.xslt&FT=Planning%20Application%20Details&PUBLIC=Y&XMLSIDE=&DAURI=PLANNING",
    "wards": "Riverside"
}