{
    "agent": null,
    "applicant": "Citescapes Limited",
    "application_number": "16L/2351",
    "application_number_provisional": null,
    "application_type": "Listed Building",
    "case_officer_name": "Anne-Marie Piedot",
    "case_officer_number": "01512333021",
    "comments_until_date": null,
    "committee_date": null,
    "current_status": "FINAL DECISION",
    "decision": "Approve with Conditions",
    "decision_date": "2017-01-20",
    "description": "To carry out internal and external alterations in connection with the change use to a restaurant (A3 Use); including alteration of existing doorway at no.54 to form a fixed window; erection of a single storey extension at 1st floor level within the existing lightwell; erection of extraction duct work within the lightwell; erection of two decorative gas lanterns either side of the main entrance at no.52.",
    "determination_level": "Case Officer",
    "development_type": "change of use (inc buildings)",
    "extract_datetime": "2017-04-23 01:27:47.047059",
    "geo_easting": 334245,
    "geo_latitude": "53.4056278246521",
    "geo_longitude": "-2.99054872489743",
    "geo_northing": 390325,
    "northgate_id": 1014580,
    "parishes": "City Centre",
    "planning_officer_name": "Anne-Marie Piedot",
    "postcode": "L2 7LQ",
    "received_date": "2016-09-12",
    "site_address": "52-54 Castle Street, Liverpool, L2 7LQ",
    "url": "http://northgate.liverpool.gov.uk/PlanningExplorer17/Generic/StdDetails.aspx?PT=Planning%20Applications%20On-Line&TYPE=PL/PlanningPK.xml&PARAM0=1014580&XSLT=/PlanningExplorer17/SiteFiles/Skins/Liverpool_WIP/xslt/PL/PLDetails.xslt&FT=Planning%20Application%20Details&PUBLIC=Y&XMLSIDE=/PlanningExplorer17/SiteFiles/Skins/Liverpool_WIP/Menus/PL.xml&DAURI=PLANNING",
    "wards": "Central"
}