{
    "agent": null,
    "applicant": "Mr & Mrs N Kalakonda",
    "application_number": "16H/2714",
    "application_number_provisional": null,
    "application_type": "Household",
    "case_officer_name": "Mika Malengo",
    "case_officer_number": null,
    "comments_until_date": "2016-12-13",
    "committee_date": null,
    "current_status": "REGISTERED",
    "decision": null,
    "decision_date": null,
    "description": "To erect first floor extension at rear, carry out external alterations to rear of property and extend terrace area to rear.",
    "determination_level": null,
    "development_type": "extension/addition: 1-storey",
    "extract_datetime": "2016-12-05 01:21:47.426126",
    "geo_easting": 340097,
    "geo_latitude": "53.3925838821556",
    "geo_longitude": "-2.90224496381204",
    "geo_northing": 388796,
    "northgate_id": 1020744,
    "parishes": "City North",
    "planning_officer_name": "Mika Malengo",
    "postcode": "L15 6YF",
    "received_date": "2016-11-03",
    "site_address": "228 Queens Drive, Liverpool, L15 6YF",
    "url": "http://northgate.liverpool.gov.uk/PlanningExplorer17/Generic/StdDetails.aspx?PT=Planning%20Applications%20On-Line&TYPE=PL/PlanningPK.xml&PARAM0=1020744&XSLT=/PlanningExplorer17/SiteFiles/Skins/Liverpool_WIP/xslt/PL/PLDetails.xslt&FT=Planning%20Application%20Details&PUBLIC=Y&XMLSIDE=/PlanningExplorer17/SiteFiles/Skins/Liverpool_WIP/Menus/PL.xml&DAURI=PLANNING",
    "wards": "Wavertree"
}